<vector xmlns:android="http://schemas.android.com/apk/res/android"
    xmlns:aapt="http://schemas.android.com/aapt"
    android:width="40dp"
    android:height="40dp"
    android:viewportWidth="40"
    android:viewportHeight="40">
  <path
      android:pathData="M20,20m-20,0a20,20 0,1 1,40 0a20,20 0,1 1,-40 0">
    <aapt:attr name="android:fillColor">
      <gradient 
          android:startX="-0"
          android:startY="20"
          android:endX="40"
          android:endY="20.128"
          android:type="linear">
        <item android:offset="0" android:color="#FFFFDFE0"/>
        <item android:offset="0.464" android:color="#FFFFFFFF"/>
        <item android:offset="1" android:color="#FFD9DAFF"/>
      </gradient>
    </aapt:attr>
  </path>
  <path
      android:pathData="M5.092,11.495C5.092,10.725 5.716,10.101 6.486,10.101H33.514C34.284,10.101 34.908,10.725 34.908,11.495V28.505C34.908,29.275 34.284,29.899 33.514,29.899H6.486C5.716,29.899 5.092,29.275 5.092,28.505V11.495Z"
      android:fillColor="#C1E1FA"/>
  <path
      android:pathData="M34.908,24.57H5.092V28.002H34.908V24.57Z"
      android:fillColor="#2587D4"/>
  <path
      android:pathData="M19.288,16.281C19.288,15.859 19.63,15.517 20.052,15.517H31.67C32.093,15.517 32.435,15.859 32.435,16.281C32.435,16.704 32.093,17.046 31.67,17.046H20.052C19.63,17.046 19.288,16.704 19.288,16.281ZM19.288,19.677C19.288,19.255 19.63,18.913 20.052,18.913H29.747C30.169,18.913 30.511,19.255 30.511,19.677C30.511,20.1 30.169,20.442 29.747,20.442H20.052C19.63,20.442 19.288,20.1 19.288,19.677Z"
      android:fillColor="#41A0EA"/>
  <path
      android:pathData="M7.552,13.699C7.552,13.218 7.942,12.828 8.423,12.828H15.791C16.272,12.828 16.662,13.218 16.662,13.699V21.052C16.662,21.533 16.272,21.923 15.791,21.923H8.423C7.942,21.923 7.552,21.533 7.552,21.052V13.699Z"
      android:fillColor="#DEF0FF"/>
  <path
      android:pathData="M13.876,16.215C13.876,17.218 13.063,18.031 12.06,18.031C11.057,18.031 10.244,17.218 10.244,16.215C10.244,15.212 11.057,14.399 12.06,14.399C13.063,14.399 13.876,15.212 13.876,16.215ZM9.206,21.266C9.206,19.694 10.48,18.42 12.052,18.42C13.624,18.42 14.898,19.694 14.898,21.266V21.923H9.206V21.266Z"
      android:fillColor="#FFCC00"/>
  <path
      android:pathData="M36.621,2.35C36.787,2.25 36.986,2.218 37.175,2.261C37.364,2.305 37.529,2.419 37.635,2.582L38.378,3.714C38.475,3.862 38.516,4.039 38.495,4.215C38.473,4.39 38.391,4.553 38.262,4.673L38.259,4.676L38.249,4.686L38.206,4.726L38.037,4.887C37.104,5.793 36.198,6.727 35.322,7.689C33.675,9.501 31.718,11.873 30.401,14.174C30.033,14.816 29.136,14.953 28.603,14.399L23.739,9.346C23.67,9.273 23.615,9.188 23.579,9.094C23.543,9 23.527,8.9 23.53,8.799C23.534,8.699 23.558,8.6 23.6,8.509C23.642,8.418 23.703,8.336 23.778,8.269L25.248,6.943C25.377,6.826 25.542,6.758 25.716,6.751C25.89,6.743 26.061,6.796 26.2,6.9L28.682,8.761C32.559,4.938 34.757,3.471 36.621,2.35Z"
      android:fillColor="#FFCC00"
      android:fillType="evenOdd"/>
</vector>
